whisperx/SubtitlesProcessor.py
whisperx/__init__.py
whisperx/__main__.py
whisperx/alignment.py
whisperx/asr.py
whisperx/audio.py
whisperx/conjunctions.py
whisperx/diarize.py
whisperx/transcribe.py
whisperx/types.py
whisperx/utils.py
whisperx/assets/mel_filters.npz
whisperx/assets/pytorch_model.bin
whisperx/vads/__init__.py
whisperx/vads/pyannote.py
whisperx/vads/silero.py
whisperx/vads/vad.py
slikts_whisperx-3.3.1.dist-info/LICENSE
slikts_whisperx-3.3.1.dist-info/METADATA
slikts_whisperx-3.3.1.dist-info/WHEEL
slikts_whisperx-3.3.1.dist-info/entry_points.txt
slikts_whisperx-3.3.1.dist-info/top_level.txt
slikts_whisperx-3.3.1.dist-info/RECORD
