Metadata-Version: 2.2
Name: slikts-whisperx
Version: 3.3.1
Summary: Time-Accurate Automatic Speech Recognition using Whisper.
Home-page: https://github.com/m-bain/whisperx
Author: Max Bain
License: BSD-2-Clause
Requires-Python: >=3.9, <3.13
License-File: LICENSE
Requires-Dist: torch>=2
Requires-Dist: torchaudio>=2
Requires-Dist: faster-whisper==1.1.0
Requires-Dist: ctranslate2<4.5.0
Requires-Dist: transformers
Requires-Dist: pandas
Requires-Dist: setuptools>=65
Requires-Dist: nltk
Requires-Dist: pyannote.audio==3.3.2
Provides-Extra: dev
Requires-Dist: pytest; extra == "dev"
Dynamic: author
Dynamic: description
Dynamic: description-content-type
Dynamic: home-page
Dynamic: license
Dynamic: provides-extra
Dynamic: requires-dist
Dynamic: requires-python
Dynamic: summary
